QuGIT_v2/__init__.py
QuGIT_v2/qgt.py
QuGIT_v2-0.2.dist-info/LICENSE
QuGIT_v2-0.2.dist-info/METADATA
QuGIT_v2-0.2.dist-info/WHEEL
QuGIT_v2-0.2.dist-info/top_level.txt
QuGIT_v2-0.2.dist-info/RECORD
