Metadata-Version: 2.1
Name: QuGIT-v2
Version: 0.2
Summary: QuGIT is an open-sourced object-oriented Python library aimed at simulating multimode quantum gaussian states.
Home-page: 
Author: Jose Manuel Montes Armenteros
Author-email: jose.manuelmontes@hotmail.com
License: BSD-3-Clause
License-File: LICENSE
Requires-Dist: numpy
Requires-Dist: scipy
